LICENSE
README.md
setup.py
sdock/__init__.py
sdock/cli.py
sdock/docker.py
sdock/marina.py
sdock/util.py
sdock.egg-info/PKG-INFO
sdock.egg-info/SOURCES.txt
sdock.egg-info/dependency_links.txt
sdock.egg-info/entry_points.txt
sdock.egg-info/requires.txt
sdock.egg-info/top_level.txt
sdock/vv/__init__.py
sdock/vv/mgr.py
sdock/vv/vagrant.py
sdock/vv/virtualbox.py
sdock/vv/boxing/__init__.py