Metadata-Version: 2.1
Name: sdock
Version: 0.1.110
Summary: My short description for my project.
Home-page: https://github.com/franceme/sdock
Author: Miles Frantz
Author-email: frantzme@vt.edu
License: UNKNOWN
Platform: UNKNOWN
Classifier: Programming Language :: Python
Classifier: Programming Language :: Python :: 3
Classifier: Programming Language :: Python :: 3.8
Requires-Python: >=3.7.0
Provides-Extra: all
Provides-Extra: mooring
Provides-Extra: vagrant
Provides-Extra: vb
License-File: LICENSE
